LICENSE.md
MANIFEST.in
README.rst
pyproject.toml
setup.cfg
setup.py
montblanc/__init__.py
montblanc/configuration.py
montblanc/factory.py
montblanc/logsetup.py
montblanc/src_types.py
montblanc.egg-info/PKG-INFO
montblanc.egg-info/SOURCES.txt
montblanc.egg-info/dependency_links.txt
montblanc.egg-info/not-zip-safe
montblanc.egg-info/requires.txt
montblanc.egg-info/top_level.txt
montblanc/api/__init__.py
montblanc/examples/MS_tf_example.py
montblanc/examples/__init__.py
montblanc/examples/standalone.py
montblanc/ext/__init__.py
montblanc/impl/__init__.py
montblanc/impl/common/__init__.py
montblanc/impl/rime/__init__.py
montblanc/impl/rime/tensorflow/RimeSolver.py
montblanc/impl/rime/tensorflow/__init__.py
montblanc/impl/rime/tensorflow/config.py
montblanc/impl/rime/tensorflow/context_help.py
montblanc/impl/rime/tensorflow/cube_dim_transcoder.py
montblanc/impl/rime/tensorflow/hypercube_proxy_metaclass.py
montblanc/impl/rime/tensorflow/init_context.py
montblanc/impl/rime/tensorflow/queue_wrapper.py
montblanc/impl/rime/tensorflow/staging_area_wrapper.py
montblanc/impl/rime/tensorflow/start_context.py
montblanc/impl/rime/tensorflow/stop_context.py
montblanc/impl/rime/tensorflow/helpers/__init__.py
montblanc/impl/rime/tensorflow/helpers/cluster_gen.py
montblanc/impl/rime/tensorflow/helpers/cluster_gen_client.py
montblanc/impl/rime/tensorflow/ms/__init__.py
montblanc/impl/rime/tensorflow/ms/ms_manager.py
montblanc/impl/rime/tensorflow/rime_ops/__init__.py
montblanc/impl/rime/tensorflow/rime_ops/abstraction.cu
montblanc/impl/rime/tensorflow/rime_ops/b_sqrt_op.h
montblanc/impl/rime/tensorflow/rime_ops/b_sqrt_op_cpu.cpp
montblanc/impl/rime/tensorflow/rime_ops/b_sqrt_op_cpu.h
montblanc/impl/rime/tensorflow/rime_ops/b_sqrt_op_gpu.cu
montblanc/impl/rime/tensorflow/rime_ops/b_sqrt_op_gpu.cuh
montblanc/impl/rime/tensorflow/rime_ops/constants.cpp
montblanc/impl/rime/tensorflow/rime_ops/constants.h
montblanc/impl/rime/tensorflow/rime_ops/create_antenna_jones_op.h
montblanc/impl/rime/tensorflow/rime_ops/create_antenna_jones_op_cpu.cpp
montblanc/impl/rime/tensorflow/rime_ops/create_antenna_jones_op_cpu.h
montblanc/impl/rime/tensorflow/rime_ops/create_antenna_jones_op_gpu.cu
